indcomp/__init__.py
indcomp/_maic.py
indcomp/_utils.py
indcomp/datasets.py
indcomp/exceptions.py
indcomp-0.1.1.dist-info/LICENSE
indcomp-0.1.1.dist-info/METADATA
indcomp-0.1.1.dist-info/WHEEL
indcomp-0.1.1.dist-info/top_level.txt
indcomp-0.1.1.dist-info/RECORD
