Metadata-Version: 2.1
Name: indcomp
Version: 0.1.1
Summary: Perform indirect treatment comparison (ITC) analyses
Home-page: https://github.com/AidanCooper/indcomp
Author: Aidan Cooper
Author-email: aidan@aidancooper.co.uk
License: MIT
Keywords: indirect,treatment,comparison,MAIC,STC,ML-NMR,adjusted
Platform: UNKNOWN
Classifier: License :: OSI Approved :: MIT License
Classifier: Programming Language :: Python :: 3
Classifier: Programming Language :: Python :: 3.10
License-File: LICENSE
Requires-Dist: numpy
Requires-Dist: scipy
Requires-Dist: pandas
Requires-Dist: matplotlib
